optimize_algorithm/__init__.py
optimize_algorithm/abc.py
optimize_algorithm/pso.py
optimize_algorithm-0.1.0.dist-info/licenses/LICENSE
optimize_algorithm-0.1.0.dist-info/METADATA
optimize_algorithm-0.1.0.dist-info/WHEEL
optimize_algorithm-0.1.0.dist-info/top_level.txt
optimize_algorithm-0.1.0.dist-info/RECORD
