Metadata-Version: 2.4
Name: optimize_algorithm
Version: 0.1.0
Summary: collection of optimization algorithms, PSO & ABC
Home-page: https://github.com/MUHAMAD30DIMAS/optimize_algorithm.git
Author: Muhamad Dimas Wijaya
License: MIT License
Requires-Python: >=3.7
License-File: LICENSE
Requires-Dist: numpy
Requires-Dist: matplotlib
Dynamic: author
Dynamic: description
Dynamic: description-content-type
Dynamic: home-page
Dynamic: license
Dynamic: license-file
Dynamic: requires-dist
Dynamic: requires-python
Dynamic: summary
